{
  "info": {
    "name": "Paydaes API",
    "description": "Covers TMS (Tenant Management Service) and CoreHR (Employee, Leave Types, Public Holidays). CoreHR requires X-Client-Id and X-Company-Id headers on every request.",
    "schema": "https://schema.getpostman.com/json/collection/v2.1.0/collection.json"
  },
  "variable": [
    { "key": "tms_base_url",   "value": "http://localhost:8081", "type": "string" },
    { "key": "corehr_base_url","value": "http://localhost:8082", "type": "string" },
    { "key": "client_id",      "value": "1",                    "type": "string" },
    { "key": "company_id",     "value": "1",                    "type": "string" }
  ],
  "item": [
    {
      "name": "TMS — Clients",
      "item": [
        {
          "name": "Create Client",
          "request": {
            "method": "POST",
            "header": [{ "key": "Content-Type", "value": "application/json" }],
            "url": {
              "raw": "{{tms_base_url}}/api/tms/clients",
              "host": ["{{tms_base_url}}"],
              "path": ["api", "tms", "clients"]
            },
            "body": {
              "mode": "raw",
              "raw": "{\n  \"name\": \"Acme Corporation\",\n  \"email\": \"admin@acme.com\",\n  \"phoneNumber\": \"+60123456789\"\n}",
              "options": { "raw": { "language": "json" } }
            }
          }
        },
        {
          "name": "Get All Clients",
          "request": {
            "method": "GET",
            "url": {
              "raw": "{{tms_base_url}}/api/tms/clients",
              "host": ["{{tms_base_url}}"],
              "path": ["api", "tms", "clients"]
            }
          }
        },
        {
          "name": "Get Client by ID",
          "request": {
            "method": "GET",
            "url": {
              "raw": "{{tms_base_url}}/api/tms/clients/{{client_id}}",
              "host": ["{{tms_base_url}}"],
              "path": ["api", "tms", "clients", "{{client_id}}"]
            }
          }
        },
        {
          "name": "Get Client by Email",
          "request": {
            "method": "GET",
            "url": {
              "raw": "{{tms_base_url}}/api/tms/clients/email/admin@acme.com",
              "host": ["{{tms_base_url}}"],
              "path": ["api", "tms", "clients", "email", "admin@acme.com"]
            }
          }
        },
        {
          "name": "Search Clients by Name",
          "request": {
            "method": "GET",
            "url": {
              "raw": "{{tms_base_url}}/api/tms/clients/search?name=Acme",
              "host": ["{{tms_base_url}}"],
              "path": ["api", "tms", "clients", "search"],
              "query": [{ "key": "name", "value": "Acme" }]
            }
          }
        },
        {
          "name": "Update Client",
          "request": {
            "method": "PUT",
            "header": [{ "key": "Content-Type", "value": "application/json" }],
            "url": {
              "raw": "{{tms_base_url}}/api/tms/clients/{{client_id}}",
              "host": ["{{tms_base_url}}"],
              "path": ["api", "tms", "clients", "{{client_id}}"]
            },
            "body": {
              "mode": "raw",
              "raw": "{\n  \"name\": \"Acme Corporation Updated\",\n  \"email\": \"admin@acme.com\",\n  \"phoneNumber\": \"+60199999999\"\n}",
              "options": { "raw": { "language": "json" } }
            }
          }
        },
        {
          "name": "Delete Client",
          "request": {
            "method": "DELETE",
            "url": {
              "raw": "{{tms_base_url}}/api/tms/clients/{{client_id}}",
              "host": ["{{tms_base_url}}"],
              "path": ["api", "tms", "clients", "{{client_id}}"]
            }
          }
        },
        {
          "name": "Get Total Client Count",
          "request": {
            "method": "GET",
            "url": {
              "raw": "{{tms_base_url}}/api/tms/clients/count",
              "host": ["{{tms_base_url}}"],
              "path": ["api", "tms", "clients", "count"]
            }
          }
        }
      ]
    },
    {
      "name": "TMS — Companies",
      "item": [
        {
          "name": "Create Company (under a Client)",
          "request": {
            "method": "POST",
            "header": [{ "key": "Content-Type", "value": "application/json" }],
            "url": {
              "raw": "{{tms_base_url}}/api/tms/companies/client/{{client_id}}",
              "host": ["{{tms_base_url}}"],
              "path": ["api", "tms", "companies", "client", "{{client_id}}"]
            },
            "body": {
              "mode": "raw",
              "raw": "{\n  \"name\": \"Acme Sdn Bhd\"\n}",
              "options": { "raw": { "language": "json" } }
            }
          }
        },
        {
          "name": "Get All Companies",
          "request": {
            "method": "GET",
            "url": {
              "raw": "{{tms_base_url}}/api/tms/companies",
              "host": ["{{tms_base_url}}"],
              "path": ["api", "tms", "companies"]
            }
          }
        },
        {
          "name": "Get Company by ID",
          "request": {
            "method": "GET",
            "url": {
              "raw": "{{tms_base_url}}/api/tms/companies/{{company_id}}",
              "host": ["{{tms_base_url}}"],
              "path": ["api", "tms", "companies", "{{company_id}}"]
            }
          }
        },
        {
          "name": "Get Companies by Client",
          "request": {
            "method": "GET",
            "url": {
              "raw": "{{tms_base_url}}/api/tms/companies/client/{{client_id}}",
              "host": ["{{tms_base_url}}"],
              "path": ["api", "tms", "companies", "client", "{{client_id}}"]
            }
          }
        },
        {
          "name": "Update Company",
          "request": {
            "method": "PUT",
            "header": [{ "key": "Content-Type", "value": "application/json" }],
            "url": {
              "raw": "{{tms_base_url}}/api/tms/companies/{{company_id}}",
              "host": ["{{tms_base_url}}"],
              "path": ["api", "tms", "companies", "{{company_id}}"]
            },
            "body": {
              "mode": "raw",
              "raw": "{\n  \"name\": \"Acme Sdn Bhd (Updated)\"\n}",
              "options": { "raw": { "language": "json" } }
            }
          }
        },
        {
          "name": "Delete Company",
          "request": {
            "method": "DELETE",
            "url": {
              "raw": "{{tms_base_url}}/api/tms/companies/{{company_id}}",
              "host": ["{{tms_base_url}}"],
              "path": ["api", "tms", "companies", "{{company_id}}"]
            }
          }
        }
      ]
    },
    {
      "name": "TMS — DB Connections (Client commondb)",
      "item": [
        {
          "name": "Save Client commondb Connection",
          "request": {
            "method": "PUT",
            "header": [{ "key": "Content-Type", "value": "application/json" }],
            "url": {
              "raw": "{{tms_base_url}}/api/tms/connections/client/{{client_id}}/commondb",
              "host": ["{{tms_base_url}}"],
              "path": ["api", "tms", "connections", "client", "{{client_id}}", "commondb"]
            },
            "body": {
              "mode": "raw",
              "raw": "{\n  \"host\": \"localhost\",\n  \"port\": 3306,\n  \"databaseName\": \"acme_commondb\",\n  \"username\": \"acme_user\",\n  \"password\": \"acme_pass123\"\n}",
              "options": { "raw": { "language": "json" } }
            }
          }
        },
        {
          "name": "Get Client commondb Connection",
          "request": {
            "method": "GET",
            "url": {
              "raw": "{{tms_base_url}}/api/tms/connections/client/{{client_id}}/commondb",
              "host": ["{{tms_base_url}}"],
              "path": ["api", "tms", "connections", "client", "{{client_id}}", "commondb"]
            }
          }
        },
        {
          "name": "Get All Client commondb Connections",
          "request": {
            "method": "GET",
            "url": {
              "raw": "{{tms_base_url}}/api/tms/connections/client/commondb",
              "host": ["{{tms_base_url}}"],
              "path": ["api", "tms", "connections", "client", "commondb"]
            }
          }
        },
        {
          "name": "Toggle Client commondb Connection Status",
          "request": {
            "method": "PATCH",
            "url": {
              "raw": "{{tms_base_url}}/api/tms/connections/client/{{client_id}}/commondb/status",
              "host": ["{{tms_base_url}}"],
              "path": ["api", "tms", "connections", "client", "{{client_id}}", "commondb", "status"]
            }
          }
        },
        {
          "name": "Delete Client commondb Connection",
          "request": {
            "method": "DELETE",
            "url": {
              "raw": "{{tms_base_url}}/api/tms/connections/client/{{client_id}}/commondb",
              "host": ["{{tms_base_url}}"],
              "path": ["api", "tms", "connections", "client", "{{client_id}}", "commondb"]
            }
          }
        }
      ]
    },
    {
      "name": "TMS — DB Connections (Company database)",
      "item": [
        {
          "name": "Save Company DB Connection",
          "request": {
            "method": "PUT",
            "header": [{ "key": "Content-Type", "value": "application/json" }],
            "url": {
              "raw": "{{tms_base_url}}/api/tms/connections/company/{{company_id}}",
              "host": ["{{tms_base_url}}"],
              "path": ["api", "tms", "connections", "company", "{{company_id}}"]
            },
            "body": {
              "mode": "raw",
              "raw": "{\n  \"host\": \"localhost\",\n  \"port\": 3307,\n  \"databaseName\": \"acme_company_db\",\n  \"username\": \"company_user\",\n  \"password\": \"company_pass456\"\n}",
              "options": { "raw": { "language": "json" } }
            }
          }
        },
        {
          "name": "Get Company DB Connection",
          "request": {
            "method": "GET",
            "url": {
              "raw": "{{tms_base_url}}/api/tms/connections/company/{{company_id}}",
              "host": ["{{tms_base_url}}"],
              "path": ["api", "tms", "connections", "company", "{{company_id}}"]
            }
          }
        },
        {
          "name": "Get All Company DB Connections by Client",
          "request": {
            "method": "GET",
            "url": {
              "raw": "{{tms_base_url}}/api/tms/connections/client/{{client_id}}/companies",
              "host": ["{{tms_base_url}}"],
              "path": ["api", "tms", "connections", "client", "{{client_id}}", "companies"]
            }
          }
        },
        {
          "name": "Toggle Company DB Connection Status",
          "request": {
            "method": "PATCH",
            "url": {
              "raw": "{{tms_base_url}}/api/tms/connections/company/{{company_id}}/status",
              "host": ["{{tms_base_url}}"],
              "path": ["api", "tms", "connections", "company", "{{company_id}}", "status"]
            }
          }
        },
        {
          "name": "Delete Company DB Connection",
          "request": {
            "method": "DELETE",
            "url": {
              "raw": "{{tms_base_url}}/api/tms/connections/company/{{company_id}}",
              "host": ["{{tms_base_url}}"],
              "path": ["api", "tms", "connections", "company", "{{company_id}}"]
            }
          }
        }
      ]
    },
    {
      "name": "CoreHR — Employees",
      "description": "All requests require X-Client-Id and X-Company-Id headers. CoreHR routes each request to the correct tenant database based on these values.",
      "item": [
        {
          "name": "Create Employee",
          "request": {
            "method": "POST",
            "header": [
              { "key": "Content-Type",  "value": "application/json" },
              { "key": "X-Client-Id",   "value": "{{client_id}}" },
              { "key": "X-Company-Id",  "value": "{{company_id}}" }
            ],
            "url": {
              "raw": "{{corehr_base_url}}/api/corehr/employees",
              "host": ["{{corehr_base_url}}"],
              "path": ["api", "corehr", "employees"]
            },
            "body": {
              "mode": "raw",
              "raw": "{\n  \"employeeId\": \"EMP-001\",\n  \"firstName\": \"Ahmad\",\n  \"lastName\": \"Razif\",\n  \"email\": \"ahmad.razif@acme.com\",\n  \"phoneNumber\": \"+60112345678\",\n  \"hireDate\": \"2024-01-15\",\n  \"jobTitle\": \"Software Engineer\",\n  \"department\": \"Engineering\",\n  \"salary\": 8500.00\n}",
              "options": { "raw": { "language": "json" } }
            }
          }
        },
        {
          "name": "Get All Employees",
          "request": {
            "method": "GET",
            "header": [
              { "key": "X-Client-Id",  "value": "{{client_id}}" },
              { "key": "X-Company-Id", "value": "{{company_id}}" }
            ],
            "url": {
              "raw": "{{corehr_base_url}}/api/corehr/employees",
              "host": ["{{corehr_base_url}}"],
              "path": ["api", "corehr", "employees"]
            }
          }
        },
        {
          "name": "Get Employee by ID",
          "request": {
            "method": "GET",
            "header": [
              { "key": "X-Client-Id",  "value": "{{client_id}}" },
              { "key": "X-Company-Id", "value": "{{company_id}}" }
            ],
            "url": {
              "raw": "{{corehr_base_url}}/api/corehr/employees/1",
              "host": ["{{corehr_base_url}}"],
              "path": ["api", "corehr", "employees", "1"]
            }
          }
        },
        {
          "name": "Get Employee by Employee ID",
          "request": {
            "method": "GET",
            "header": [
              { "key": "X-Client-Id",  "value": "{{client_id}}" },
              { "key": "X-Company-Id", "value": "{{company_id}}" }
            ],
            "url": {
              "raw": "{{corehr_base_url}}/api/corehr/employees/employee-id/EMP-001",
              "host": ["{{corehr_base_url}}"],
              "path": ["api", "corehr", "employees", "employee-id", "EMP-001"]
            }
          }
        },
        {
          "name": "Get Employee by Email",
          "request": {
            "method": "GET",
            "header": [
              { "key": "X-Client-Id",  "value": "{{client_id}}" },
              { "key": "X-Company-Id", "value": "{{company_id}}" }
            ],
            "url": {
              "raw": "{{corehr_base_url}}/api/corehr/employees/email/ahmad.razif@acme.com",
              "host": ["{{corehr_base_url}}"],
              "path": ["api", "corehr", "employees", "email", "ahmad.razif@acme.com"]
            }
          }
        },
        {
          "name": "Get Employees by Department",
          "request": {
            "method": "GET",
            "header": [
              { "key": "X-Client-Id",  "value": "{{client_id}}" },
              { "key": "X-Company-Id", "value": "{{company_id}}" }
            ],
            "url": {
              "raw": "{{corehr_base_url}}/api/corehr/employees/department/Engineering",
              "host": ["{{corehr_base_url}}"],
              "path": ["api", "corehr", "employees", "department", "Engineering"]
            }
          }
        },
        {
          "name": "Get Employees by Status",
          "request": {
            "method": "GET",
            "header": [
              { "key": "X-Client-Id",  "value": "{{client_id}}" },
              { "key": "X-Company-Id", "value": "{{company_id}}" }
            ],
            "url": {
              "raw": "{{corehr_base_url}}/api/corehr/employees/status/ACTIVE",
              "host": ["{{corehr_base_url}}"],
              "path": ["api", "corehr", "employees", "status", "ACTIVE"]
            }
          }
        },
        {
          "name": "Search Employees by Name",
          "request": {
            "method": "GET",
            "header": [
              { "key": "X-Client-Id",  "value": "{{client_id}}" },
              { "key": "X-Company-Id", "value": "{{company_id}}" }
            ],
            "url": {
              "raw": "{{corehr_base_url}}/api/corehr/employees/search?name=Ahmad",
              "host": ["{{corehr_base_url}}"],
              "path": ["api", "corehr", "employees", "search"],
              "query": [{ "key": "name", "value": "Ahmad" }]
            }
          }
        },
        {
          "name": "Update Employee",
          "request": {
            "method": "PUT",
            "header": [
              { "key": "Content-Type",  "value": "application/json" },
              { "key": "X-Client-Id",   "value": "{{client_id}}" },
              { "key": "X-Company-Id",  "value": "{{company_id}}" }
            ],
            "url": {
              "raw": "{{corehr_base_url}}/api/corehr/employees/1",
              "host": ["{{corehr_base_url}}"],
              "path": ["api", "corehr", "employees", "1"]
            },
            "body": {
              "mode": "raw",
              "raw": "{\n  \"employeeId\": \"EMP-001\",\n  \"firstName\": \"Ahmad\",\n  \"lastName\": \"Razif\",\n  \"email\": \"ahmad.razif@acme.com\",\n  \"phoneNumber\": \"+60112345678\",\n  \"hireDate\": \"2024-01-15\",\n  \"jobTitle\": \"Senior Software Engineer\",\n  \"department\": \"Engineering\",\n  \"salary\": 10000.00,\n  \"status\": \"ACTIVE\"\n}",
              "options": { "raw": { "language": "json" } }
            }
          }
        },
        {
          "name": "Update Employee Status",
          "request": {
            "method": "PATCH",
            "header": [
              { "key": "X-Client-Id",  "value": "{{client_id}}" },
              { "key": "X-Company-Id", "value": "{{company_id}}" }
            ],
            "url": {
              "raw": "{{corehr_base_url}}/api/corehr/employees/1/status?status=INACTIVE",
              "host": ["{{corehr_base_url}}"],
              "path": ["api", "corehr", "employees", "1", "status"],
              "query": [{ "key": "status", "value": "INACTIVE" }]
            }
          }
        },
        {
          "name": "Delete Employee",
          "request": {
            "method": "DELETE",
            "header": [
              { "key": "X-Client-Id",  "value": "{{client_id}}" },
              { "key": "X-Company-Id", "value": "{{company_id}}" }
            ],
            "url": {
              "raw": "{{corehr_base_url}}/api/corehr/employees/1",
              "host": ["{{corehr_base_url}}"],
              "path": ["api", "corehr", "employees", "1"]
            }
          }
        },
        {
          "name": "Get Employee Count by Status",
          "request": {
            "method": "GET",
            "header": [
              { "key": "X-Client-Id",  "value": "{{client_id}}" },
              { "key": "X-Company-Id", "value": "{{company_id}}" }
            ],
            "url": {
              "raw": "{{corehr_base_url}}/api/corehr/employees/count/status/ACTIVE",
              "host": ["{{corehr_base_url}}"],
              "path": ["api", "corehr", "employees", "count", "status", "ACTIVE"]
            }
          }
        }
      ]
    },
    {
      "name": "CoreHR — Leave Types",
      "description": "Client-level shared leave type configuration. Stored in the client's commondb. Requires X-Client-Id and X-Company-Id headers.",
      "item": [
        {
          "name": "Create Leave Type",
          "request": {
            "method": "POST",
            "header": [
              { "key": "Content-Type",  "value": "application/json" },
              { "key": "X-Client-Id",   "value": "{{client_id}}" },
              { "key": "X-Company-Id",  "value": "{{company_id}}" }
            ],
            "url": {
              "raw": "{{corehr_base_url}}/api/corehr/leave-types",
              "host": ["{{corehr_base_url}}"],
              "path": ["api", "corehr", "leave-types"]
            },
            "body": {
              "mode": "raw",
              "raw": "{\n  \"code\": \"ANNUAL\",\n  \"name\": \"Annual Leave\",\n  \"maxDaysPerYear\": 14,\n  \"isPaid\": true,\n  \"carryForwardDays\": 5\n}",
              "options": { "raw": { "language": "json" } }
            }
          }
        },
        {
          "name": "Get All Leave Types",
          "request": {
            "method": "GET",
            "header": [
              { "key": "X-Client-Id",  "value": "{{client_id}}" },
              { "key": "X-Company-Id", "value": "{{company_id}}" }
            ],
            "url": {
              "raw": "{{corehr_base_url}}/api/corehr/leave-types",
              "host": ["{{corehr_base_url}}"],
              "path": ["api", "corehr", "leave-types"]
            }
          }
        },
        {
          "name": "Get Active Leave Types",
          "request": {
            "method": "GET",
            "header": [
              { "key": "X-Client-Id",  "value": "{{client_id}}" },
              { "key": "X-Company-Id", "value": "{{company_id}}" }
            ],
            "url": {
              "raw": "{{corehr_base_url}}/api/corehr/leave-types/active",
              "host": ["{{corehr_base_url}}"],
              "path": ["api", "corehr", "leave-types", "active"]
            }
          }
        },
        {
          "name": "Get Leave Type by ID",
          "request": {
            "method": "GET",
            "header": [
              { "key": "X-Client-Id",  "value": "{{client_id}}" },
              { "key": "X-Company-Id", "value": "{{company_id}}" }
            ],
            "url": {
              "raw": "{{corehr_base_url}}/api/corehr/leave-types/1",
              "host": ["{{corehr_base_url}}"],
              "path": ["api", "corehr", "leave-types", "1"]
            }
          }
        },
        {
          "name": "Get Leave Type by Code",
          "request": {
            "method": "GET",
            "header": [
              { "key": "X-Client-Id",  "value": "{{client_id}}" },
              { "key": "X-Company-Id", "value": "{{company_id}}" }
            ],
            "url": {
              "raw": "{{corehr_base_url}}/api/corehr/leave-types/code/ANNUAL",
              "host": ["{{corehr_base_url}}"],
              "path": ["api", "corehr", "leave-types", "code", "ANNUAL"]
            }
          }
        },
        {
          "name": "Update Leave Type",
          "request": {
            "method": "PUT",
            "header": [
              { "key": "Content-Type",  "value": "application/json" },
              { "key": "X-Client-Id",   "value": "{{client_id}}" },
              { "key": "X-Company-Id",  "value": "{{company_id}}" }
            ],
            "url": {
              "raw": "{{corehr_base_url}}/api/corehr/leave-types/1",
              "host": ["{{corehr_base_url}}"],
              "path": ["api", "corehr", "leave-types", "1"]
            },
            "body": {
              "mode": "raw",
              "raw": "{\n  \"code\": \"ANNUAL\",\n  \"name\": \"Annual Leave\",\n  \"maxDaysPerYear\": 16,\n  \"isPaid\": true,\n  \"carryForwardDays\": 7\n}",
              "options": { "raw": { "language": "json" } }
            }
          }
        },
        {
          "name": "Toggle Leave Type Status",
          "request": {
            "method": "PATCH",
            "header": [
              { "key": "X-Client-Id",  "value": "{{client_id}}" },
              { "key": "X-Company-Id", "value": "{{company_id}}" }
            ],
            "url": {
              "raw": "{{corehr_base_url}}/api/corehr/leave-types/1/status",
              "host": ["{{corehr_base_url}}"],
              "path": ["api", "corehr", "leave-types", "1", "status"]
            }
          }
        },
        {
          "name": "Delete Leave Type",
          "request": {
            "method": "DELETE",
            "header": [
              { "key": "X-Client-Id",  "value": "{{client_id}}" },
              { "key": "X-Company-Id", "value": "{{company_id}}" }
            ],
            "url": {
              "raw": "{{corehr_base_url}}/api/corehr/leave-types/1",
              "host": ["{{corehr_base_url}}"],
              "path": ["api", "corehr", "leave-types", "1"]
            }
          }
        }
      ]
    },
    {
      "name": "CoreHR — Public Holidays",
      "description": "Client-level public holiday calendar. Stored in the client's commondb. Requires X-Client-Id and X-Company-Id headers.",
      "item": [
        {
          "name": "Add Public Holiday",
          "request": {
            "method": "POST",
            "header": [
              { "key": "Content-Type",  "value": "application/json" },
              { "key": "X-Client-Id",   "value": "{{client_id}}" },
              { "key": "X-Company-Id",  "value": "{{company_id}}" }
            ],
            "url": {
              "raw": "{{corehr_base_url}}/api/corehr/public-holidays",
              "host": ["{{corehr_base_url}}"],
              "path": ["api", "corehr", "public-holidays"]
            },
            "body": {
              "mode": "raw",
              "raw": "{\n  \"holidayDate\": \"2025-01-01\",\n  \"name\": \"New Year's Day\"\n}",
              "options": { "raw": { "language": "json" } }
            }
          }
        },
        {
          "name": "Get Holiday by ID",
          "request": {
            "method": "GET",
            "header": [
              { "key": "X-Client-Id",  "value": "{{client_id}}" },
              { "key": "X-Company-Id", "value": "{{company_id}}" }
            ],
            "url": {
              "raw": "{{corehr_base_url}}/api/corehr/public-holidays/1",
              "host": ["{{corehr_base_url}}"],
              "path": ["api", "corehr", "public-holidays", "1"]
            }
          }
        },
        {
          "name": "Get Holidays by Year",
          "request": {
            "method": "GET",
            "header": [
              { "key": "X-Client-Id",  "value": "{{client_id}}" },
              { "key": "X-Company-Id", "value": "{{company_id}}" }
            ],
            "url": {
              "raw": "{{corehr_base_url}}/api/corehr/public-holidays/year/2025",
              "host": ["{{corehr_base_url}}"],
              "path": ["api", "corehr", "public-holidays", "year", "2025"]
            }
          }
        },
        {
          "name": "Get Active Holidays by Year",
          "request": {
            "method": "GET",
            "header": [
              { "key": "X-Client-Id",  "value": "{{client_id}}" },
              { "key": "X-Company-Id", "value": "{{company_id}}" }
            ],
            "url": {
              "raw": "{{corehr_base_url}}/api/corehr/public-holidays/year/2025/active",
              "host": ["{{corehr_base_url}}"],
              "path": ["api", "corehr", "public-holidays", "year", "2025", "active"]
            }
          }
        },
        {
          "name": "Update Public Holiday",
          "request": {
            "method": "PUT",
            "header": [
              { "key": "Content-Type",  "value": "application/json" },
              { "key": "X-Client-Id",   "value": "{{client_id}}" },
              { "key": "X-Company-Id",  "value": "{{company_id}}" }
            ],
            "url": {
              "raw": "{{corehr_base_url}}/api/corehr/public-holidays/1",
              "host": ["{{corehr_base_url}}"],
              "path": ["api", "corehr", "public-holidays", "1"]
            },
            "body": {
              "mode": "raw",
              "raw": "{\n  \"holidayDate\": \"2025-01-01\",\n  \"name\": \"New Year's Day 2025\"\n}",
              "options": { "raw": { "language": "json" } }
            }
          }
        },
        {
          "name": "Delete Public Holiday",
          "request": {
            "method": "DELETE",
            "header": [
              { "key": "X-Client-Id",  "value": "{{client_id}}" },
              { "key": "X-Company-Id", "value": "{{company_id}}" }
            ],
            "url": {
              "raw": "{{corehr_base_url}}/api/corehr/public-holidays/1",
              "host": ["{{corehr_base_url}}"],
              "path": ["api", "corehr", "public-holidays", "1"]
            }
          }
        }
      ]
    }
  ]
}
